Test/.history/Lights_20250416164054.vhdl
library IEEE;
use IEEE.STD_LOGIC_1164.ALL;
use IEEE.NUMERIC_STD.ALL;

entity Lights is
    Port (
        clk         : in  STD_LOGIC;
        reset       : in  STD_LOGIC;
        ped_button  : in  STD_LOGIC;
        red_light   : out STD_LOGIC;
        yellow_light: out STD_LOGIC;
        green_light : out STD_LOGIC;
        ped_signal  : out STD_LOGIC
    );
end Lights;

architecture Behavioral of Lights is
    type state_type is (RED, GREEN, YELLOW);
    signal current_state, next_state : state_type;
    signal counter : integer := 0;
    constant TIMEOUT : integer := 50;
begin

    -- State machine
    process(clk, reset)
    begin
        if reset = '1' then
            current_state <= RED;
            counter <= 0;
        elsif rising_edge(clk) then
            if ped_button = '0' then
                if counter < TIMEOUT then
                    counter <= counter + 1;
                else
                    current_state <= next_state;
                    counter <= 0;
                end if;
            else
                current_state <= RED; -- Force RED if button is pressed
                counter <= 0;
            end if;
        end if;
    end process;

    -- State transitions
    process(current_state)
    begin
        case current_state is
            when RED    => next_state <= GREEN;
            when GREEN  => next_state <= YELLOW;
            when YELLOW => next_state <= RED;
            when others => next_state <= RED;
        end case;
    end process;

    -- Output logic
    process(current_state, ped_button)
    begin
        red_light    <= '0';
        yellow_light <= '0';
        green_light  <= '0';
        ped_signal   <= '0';

        if ped_button = '1' then
            red_light  <= '1';
            ped_signal <= '1';
        else
            case current_state is
                when RED =>
                    red_light <= '1';
                when GREEN =>
                    green_light <= '1';
                when YELLOW =>
                    yellow_light <= '1';
                when others =>
                    null;
            end case;
        end if;
    end process;

end Behavioral;

Test/Lights_tb.vhdl
library IEEE;
use IEEE.STD_LOGIC_1164.ALL;
use IEEE.NUMERIC_STD.ALL;

entity Lights_tb is
end Lights_tb;

architecture Behavioral of Lights_tb is

    -- Component Declaration
    component Lights
        Port (
            clk         : in  STD_LOGIC;
            reset       : in  STD_LOGIC;
            ped_button  : in  STD_LOGIC;
            red_light   : out STD_LOGIC;
            yellow_light: out STD_LOGIC;
            green_light : out STD_LOGIC;
            ped_signal  : out STD_LOGIC
        );
    end component;

    -- Signals for simulation
    signal clk         : STD_LOGIC := '0';
    signal reset       : STD_LOGIC := '1';
    signal ped_button  : STD_LOGIC := '0';
    signal red_light   : STD_LOGIC;
    signal yellow_light: STD_LOGIC;
    signal green_light : STD_LOGIC;
    signal ped_signal  : STD_LOGIC;

    constant CLK_PERIOD : time := 10 ns;

begin

    -- Instantiate the traffic light
    uut: Lights
        Port Map (
            clk         => clk,
            reset       => reset,
            ped_button  => ped_button,
            red_light   => red_light,
            yellow_light=> yellow_light,
            green_light => green_light,
            ped_signal  => ped_signal
        );

    -- Clock generation
    clk_process :process
    begin
        while true loop
            clk <= '0';
            wait for CLK_PERIOD / 2;
            clk <= '1';
            wait for CLK_PERIOD / 2;
        end loop;
    end process;

    -- Stimulus
    stim_proc: process
    begin
        -- Hold reset
        wait for 20 ns;
        reset <= '0';

        -- Run normal cycle
        wait for 400 ns;

        -- Pedestrian presses the button
        ped_button <= '1';
        wait for 50 ns;
        ped_button <= '0';

        -- Wait for system to return to normal cycle
        wait for 500 ns;

        -- Press button again
        ped_button <= '1';
        wait for 30 ns;
        ped_button <= '0';

        -- Run a bit more
        wait for 500 ns;

        wait;
    end process;

end Behavioral;

Test/wave.vcd
$date
  Wed Apr 16 16:43:38 2025
$end
$version
  GHDL v0
$end
$timescale
  1 fs
$end
$scope module standard $end
$upscope $end
$scope module std_logic_1164 $end
$upscope $end
$scope module numeric_std $end
$upscope $end
$scope module lights_tb $end
$var reg 1 ! clk $end
$var reg 1 " reset $end
$var reg 1 # ped_button $end
$var reg 1 $ red_light $end
$var reg 1 % yellow_light $end
$var reg 1 & green_light $end
$var reg 1 ' ped_signal $end
$scope module uut $end
$var reg 1 ( clk $end
$var reg 1 ) reset $end
$var reg 1 * ped_button $end
$var reg 1 + red_light $end
$var reg 1 , yellow_light $end
$var reg 1 - green_light $end
$var reg 1 . ped_signal $end
$comment current_state is not handled $end
$comment next_state is not handled $end
$var integer 32 / counter $end
$upscope $end
$upscope $end
$enddefinitions $end
#0
0!
1"
0#
1$
0%
0&
0'
0(
1)
0*
1+
0,
0-
0.
b0 /
#5000000
1!
1(
#10000000
0!
0(
#15000000
1!
1(
#20000000
0!
0"
0(
0)
#25000000
1!
1(
b1 /
#30000000
0!
0(
#35000000
1!
1(
b10 /
#40000000
0!
0(
#45000000
1!
1(
b11 /
#50000000
0!
0(
#55000000
1!
1(
b100 /
#60000000
0!
0(
#65000000
1!
1(
b101 /
#70000000
0!
0(
#75000000
1!
1(
b110 /
#80000000
0!
0(
#85000000
1!
1(
b111 /
#90000000
0!
0(
#95000000
1!
1(
b1000 /
#100000000
0!
0(
#105000000
1!
1(
b1001 /
#110000000
0!
0(
#115000000
1!
1(
b1010 /
#120000000
0!
0(
#125000000
1!
1(
b1011 /
#130000000
0!
0(
#135000000
1!
1(
b1100 /
#140000000
0!
0(
#145000000
1!
1(
b1101 /
#150000000
0!
0(
#155000000
1!
1(
b1110 /
#160000000
0!
0(
#165000000
1!
1(
b1111 /
#170000000
0!
0(
#175000000
1!
1(
b10000 /
#180000000
0!
0(
#185000000
1!
1(
b10001 /
#190000000
0!
0(
#195000000
1!
1(
b10010 /
#200000000
0!
0(
#205000000
1!
1(
b10011 /
#210000000
0!
0(
#215000000
1!
1(
b10100 /
#220000000
0!
0(
#225000000
1!
1(
b10101 /
#230000000
0!
0(
#235000000
1!
1(
b10110 /
#240000000
0!
0(
#245000000
1!
1(
b10111 /
#250000000
0!
0(
#255000000
1!
1(
b11000 /
#260000000
0!
0(
#265000000
1!
1(
b11001 /
#270000000
0!
0(
#275000000
1!
1(
b11010 /
#280000000
0!
0(
#285000000
1!
1(
b11011 /
#290000000
0!
0(
#295000000
1!
1(
b11100 /
#300000000
0!
0(
#305000000
1!
1(
b11101 /
#310000000
0!
0(
#315000000
1!
1(
b11110 /
#320000000
0!
0(
#325000000
1!
1(
b11111 /
#330000000
0!
0(
#335000000
1!
1(
b100000 /
#340000000
0!
0(
#345000000
1!
1(
b100001 /
#350000000
0!
0(
#355000000
1!
1(
b100010 /
#360000000
0!
0(
#365000000
1!
1(
b100011 /
#370000000
0!
0(
#375000000
1!
1(
b100100 /
#380000000
0!
0(
#385000000
1!
1(
b100101 /
#390000000
0!
0(
#395000000
1!
1(
b100110 /
#400000000
0!
0(
#405000000
1!
1(
b100111 /
#410000000
0!
0(
#415000000
1!
1(
b101000 /
#420000000
0!
1#
1'
0(
1*
1+
1.
#425000000
1!
1(
b0 /
#430000000
0!
0(
#435000000
1!
1(
#440000000
0!
0(
#445000000
1!
1(
#450000000
0!
0(
#455000000
1!
1(
#460000000
0!
0(
#465000000
1!
1(
#470000000
0!
0#
0'
0(
0*
1+
0.
#475000000
1!
1(
b1 /
#480000000
0!
0(
#485000000
1!
1(
b10 /
#490000000
0!
0(
#495000000
1!
1(
b11 /
#500000000
0!
0(
#505000000
1!
1(
b100 /
#510000000
0!
0(
#515000000
1!
1(
b101 /
#520000000
0!
0(
#525000000
1!
1(
b110 /
#530000000
0!
0(
#535000000
1!
1(
b111 /
#540000000
0!
0(
#545000000
1!
1(
b1000 /
#550000000
0!
0(
#555000000
1!
1(
b1001 /
#560000000
0!
0(
#565000000
1!
1(
b1010 /
#570000000
0!
0(
#575000000
1!
1(
b1011 /
#580000000
0!
0(
#585000000
1!
1(
b1100 /
#590000000
0!
0(
#595000000
1!
1(
b1101 /
#600000000
0!
0(
#605000000
1!
1(
b1110 /
#610000000
0!
0(
#615000000
1!
1(
b1111 /
#620000000
0!
0(
#625000000
1!
1(
b10000 /
#630000000
0!
0(
#635000000
1!
1(
b10001 /
#640000000
0!
0(
#645000000
1!
1(
b10010 /
#650000000
0!
0(
#655000000
1!
1(
b10011 /
#660000000
0!
0(
#665000000
1!
1(
b10100 /
#670000000
0!
0(
#675000000
1!
1(
b10101 /
#680000000
0!
0(
#685000000
1!
1(
b10110 /
#690000000
0!
0(
#695000000
1!
1(
b10111 /
#700000000
0!
0(
#705000000
1!
1(
b11000 /
#710000000
0!
0(
#715000000
1!
1(
b11001 /
#720000000
0!
0(
#725000000
1!
1(
b11010 /
#730000000
0!
0(
#735000000
1!
1(
b11011 /
#740000000
0!
0(
#745000000
1!
1(
b11100 /
#750000000
0!
0(
#755000000
1!
1(
b11101 /
#760000000
0!
0(
#765000000
1!
1(
b11110 /
#770000000
0!
0(
#775000000
1!
1(
b11111 /
#780000000
0!
0(
#785000000
1!
1(
b100000 /
#790000000
0!
0(
#795000000
1!
1(
b100001 /
#800000000
0!
0(
#805000000
1!
1(
b100010 /
#810000000
0!
0(
#815000000
1!
1(
b100011 /
#820000000
0!
0(
#825000000
1!
1(
b100100 /
#830000000
0!
0(
#835000000
1!
1(
b100101 /
#840000000
0!
0(
#845000000
1!
1(
b100110 /
#850000000
0!
0(
#855000000
1!
1(
b100111 /
#860000000
0!
0(
#865000000
1!
1(
b101000 /
#870000000
0!
0(
#875000000
1!
1(
b101001 /
#880000000
0!
0(
#885000000
1!
1(
b101010 /
#890000000
0!
0(
#895000000
1!
1(
b101011 /
#900000000
0!
0(
#905000000
1!
1(
b101100 /
#910000000
0!
0(
#915000000
1!
1(
b101101 /
#920000000
0!
0(
#925000000
1!
1(
b101110 /
#930000000
0!
0(
#935000000
1!
1(
b101111 /
#940000000
0!
0(
#945000000
1!
1(
b110000 /
#950000000
0!
0(
#955000000
1!
1(
b110001 /
#960000000
0!
0(
#965000000
1!
1(
b110010 /
#970000000
0!
1#
1'
0(
1*
1+
1.
#975000000
1!
1(
b0 /
#980000000
0!
0(
#985000000
1!
1(
#990000000
0!
0(
#995000000
1!
1(
#1000000000
0!
0#
0'
0(
0*
1+
0.
#1005000000
1!
1(
b1 /
#1010000000
0!
0(
#1015000000
1!
1(
b10 /
#1020000000
0!
0(
#1025000000
1!
1(
b11 /
#1030000000
0!
0(
#1035000000
1!
1(
b100 /
#1040000000
0!
0(
#1045000000
1!
1(
b101 /
#1050000000
0!
0(
#1055000000
1!
1(
b110 /
#1060000000
0!
0(
#1065000000
1!
1(
b111 /
#1070000000
0!
0(
#1075000000
1!
1(
b1000 /
#1080000000
0!
0(
#1085000000
1!
1(
b1001 /
#1090000000
0!
0(
#1095000000
1!
1(
b1010 /
#1100000000
0!
0(
#1105000000
1!
1(
b1011 /
#1110000000
0!
0(
#1115000000
1!
1(
b1100 /
#1120000000
0!
0(
#1125000000
1!
1(
b1101 /
#1130000000
0!
0(
#1135000000
1!
1(
b1110 /
#1140000000
0!
0(
#1145000000
1!
1(
b1111 /
#1150000000
0!
0(
#1155000000
1!
1(
b10000 /
#1160000000
0!
0(
#1165000000
1!
1(
b10001 /
#1170000000
0!
0(
#1175000000
1!
1(
b10010 /
#1180000000
0!
0(
#1185000000
1!
1(
b10011 /
#1190000000
0!
0(
#1195000000
1!
1(
b10100 /
#1200000000
0!
0(
#1205000000
1!
1(
b10101 /
#1210000000
0!
0(
#1215000000
1!
1(
b10110 /
#1220000000
0!
0(
#1225000000
1!
1(
b10111 /
#1230000000
0!
0(
#1235000000
1!
1(
b11000 /
#1240000000
0!
0(
#1245000000
1!
1(
b11001 /
#1250000000
0!
0(
#1255000000
1!
1(
b11010 /
#1260000000
0!
0(
#1265000000
1!
1(
b11011 /
#1270000000
0!
0(
#1275000000
1!
1(
b11100 /
#1280000000
0!
0(
#1285000000
1!
1(
b11101 /
#1290000000
0!
0(
#1295000000
1!
1(
b11110 /
#1300000000
0!
0(
#1305000000
1!
1(
b11111 /
#1310000000
0!
0(
#1315000000
1!
1(
b100000 /
#1320000000
0!
0(
#1325000000
1!
1(
b100001 /
#1330000000
0!
0(
#1335000000
1!
1(
b100010 /
#1340000000
0!
0(
#1345000000
1!
1(
b100011 /
#1350000000
0!
0(
#1355000000
1!
1(
b100100 /
#1360000000
0!
0(
#1365000000
1!
1(
b100101 /
#1370000000
0!
0(
#1375000000
1!
1(
b100110 /
#1380000000
0!
0(
#1385000000
1!
1(
b100111 /
#1390000000
0!
0(
#1395000000
1!
1(
b101000 /
#1400000000
0!
0(
#1405000000
1!
1(
b101001 /
#1410000000
0!
0(
#1415000000
1!
1(
b101010 /
#1420000000
0!
0(
#1425000000
1!
1(
b101011 /
#1430000000
0!
0(
#1435000000
1!
1(
b101100 /
#1440000000
0!
0(
#1445000000
1!
1(
b101101 /
#1450000000
0!
0(
#1455000000
1!
1(
b101110 /
#1460000000
0!
0(
#1465000000
1!
1(
b101111 /
#1470000000
0!
0(
#1475000000
1!
1(
b110000 /
#1480000000
0!
0(
#1485000000
1!
1(
b110001 /
#1490000000
0!
0(
#1495000000
1!
1(
b110010 /
#1500000000
0!
0(
#1505000000
1!
0$
1&
1(
0+
1-
b0 /
#1510000000
0!
0(
#1515000000
1!
1(
b1 /
#1520000000
0!
0(
#1525000000
1!
1(
b10 /
#1530000000
0!
0(
#1535000000
1!
1(
b11 /
#1540000000
0!
0(
#1545000000
1!
1(
b100 /
#1550000000
0!
0(
#1555000000
1!
1(
b101 /
#1560000000
0!
0(
#1565000000
1!
1(
b110 /
#1570000000
0!
0(
#1575000000
1!
1(
b111 /
#1580000000
0!
0(
#1585000000
1!
1(
b1000 /
#1590000000
0!
0(
#1595000000
1!
1(
b1001 /
#1600000000
0!
0(
#1605000000
1!
1(
b1010 /
#1610000000
0!
0(
#1615000000
1!
1(
b1011 /
#1620000000
0!
0(
#1625000000
1!
1(
b1100 /
#1630000000
0!
0(
#1635000000
1!
1(
b1101 /
#1640000000
0!
0(
#1645000000
1!
1(
b1110 /
#1650000000
0!
0(
#1655000000
1!
1(
b1111 /
#1660000000
0!
0(
#1665000000
1!
1(
b10000 /
#1670000000
0!
0(
#1675000000
1!
1(
b10001 /
#1680000000
0!
0(
#1685000000
1!
1(
b10010 /
#1690000000
0!
0(
#1695000000
1!
1(
b10011 /
#1700000000
0!
0(
#1705000000
1!
1(
b10100 /
#1710000000
0!
0(
#1715000000
1!
1(
b10101 /
#1720000000
0!
0(
#1725000000
1!
1(
b10110 /
#1730000000
0!
0(
#1735000000
1!
1(
b10111 /
#1740000000
0!
0(
#1745000000
1!
1(
b11000 /
#1750000000
0!
0(
#1755000000
1!
1(
b11001 /
#1760000000
0!
0(
#1765000000
1!
1(
b11010 /
#1770000000
0!
0(
#1775000000
1!
1(
b11011 /
#1780000000
0!
0(
#1785000000
1!
1(
b11100 /
#1790000000
0!
0(
#1795000000
1!
1(
b11101 /
#1800000000
0!
0(
#1805000000
1!
1(
b11110 /
#1810000000
0!
0(
#1815000000
1!
1(
b11111 /
#1820000000
0!
0(
#1825000000
1!
1(
b100000 /
#1830000000
0!
0(
#1835000000
1!
1(
b100001 /
#1840000000
0!
0(
#1845000000
1!
1(
b100010 /
#1850000000
0!
0(
#1855000000
1!
1(
b100011 /
#1860000000
0!
0(
#1865000000
1!
1(
b100100 /
#1870000000
0!
0(
#1875000000
1!
1(
b100101 /
#1880000000
0!
0(
#1885000000
1!
1(
b100110 /
#1890000000
0!
0(
#1895000000
1!
1(
b100111 /
#1900000000
0!
0(
#1905000000
1!
1(
b101000 /
#1910000000
0!
0(
#1915000000
1!
1(
b101001 /
#1920000000
0!
0(
#1925000000
1!
1(
b101010 /
#1930000000
0!
0(
#1935000000
1!
1(
b101011 /
#1940000000
0!
0(
#1945000000
1!
1(
b101100 /
#1950000000
0!
0(
#1955000000
1!
1(
b101101 /
#1960000000
0!
0(
#1965000000
1!
1(
b101110 /
#1970000000
0!
0(
#1975000000
1!
1(
b101111 /
#1980000000
0!
0(
#1985000000
1!
1(
b110000 /
#1990000000
0!
0(
#1995000000
1!
1(
b110001 /
