AND_Dff/AND_Dff.v
module AND_Dff (
    input A, 
    input B, 
    input C, 
    output reg Q
);

and(clock, B, C);

always @(posedge clock) begin
    Q <= A;
end

endmodule

AND_Dff/AND_Dff_tb.v
`include "AND_Dff.v"

module AND_Dff_tb;

    reg A, B, C;
    wire Q;

    AND_Dff uut (
        .A(A),
        .B(B),
        .C(C),
        .Q(Q)
    );

    initial begin
        $dumpfile("AND_Dff_tb.vcd");
        $dumpvars(0, AND_Dff_tb);
        
        $display("A\tB\tC\tQ");
        $monitor("%b\t%b\t%b\t%b", A, B, C, Q);

        A = 0;        B = 0;        C = 0;
        #10;

        C = 1;
        #10;

        B = 1;        C = 0;        
        #10;

        C = 1;        
        #10;
        
        A = 1;        B = 0;        C = 0;
        #10;

        C = 1;
        #10;

        B = 1;        C = 0;        
        #10;

        C = 1;        
        #10;

        $display("Test complete");
        $finish;
    end

endmodule

AND_Dff/AND_Dff_tb.vcd
$date
	Wed Feb 05 15:38:16 2025
$end
$version
	Icarus Verilog
$end
$timescale
	1s
$end
$scope module AND_Dff_tb $end
$var wire 1 ! Q $end
$var reg 1 " A $end
$var reg 1 # B $end
$var reg 1 $ C $end
$scope module uut $end
$var wire 1 " A $end
$var wire 1 # B $end
$var wire 1 $ C $end
$var wire 1 % clock $end
$var reg 1 ! Q $end
$upscope $end
$upscope $end
$enddefinitions $end
$comment Show the parameter values. $end
$dumpall
$end
#0
$dumpvars
0%
0$
0#
0"
x!
$end
#10
1$
#20
0$
1#
#30
0!
1%
1$
#40
0%
0$
0#
1"
#50
1$
#60
0$
1#
#70
1!
1%
1$
